{
  "continentsCode": {
    "AF": "Africa",
    "AS": "Asia",
    "EU": "Europa",
    "NA": "America del Nord",
    "OC": "Oceania",
    "SA": "America del Sud",
    "AN": "Antartide"
  },
  "countriesCode": {
    "US": "Stati Uniti",
    "FR": "Francia",
    "DE": "Germania",
    "ES": "Spagna",
    "IT": "Italia",
    "GB": "Regno Unito",
    "HR": "Croazia",
    "CA": "Canada",
    "AU": "Australia",
    "CN": "Cina",
    "JP": "Giappone",
    "IN": "India",
    "BR": "Brasile",
    "RU": "Russia",
    "MX": "Messico",
    "ZA": "Sudafrica",
    "SA": "Arabia Saudita",
    "EG": "Egitto",
    "NG": "Nigeria",
    "KE": "Kenya",
    "MA": "Marocco",
    "TN": "Tunisia",
    "MK": "Macedonia del Nord",
    "AR": "Argentina",
    "TR": "Turchia",
    "ID": "Indonesia",
    "KR": "Corea del Sud",
    "NL": "Paesi Bassi",
    "SE": "Svezia",
    "CH": "Svizzera",
    "BE": "Belgio",
    "AT": "Austria",
    "PL": "Polonia",
    "NO": "Norvegia",
    "FI": "Finlandia",
    "DK": "Danimarca",
    "GR": "Grecia",
    "PT": "Portogallo",
    "HU": "Ungheria",
    "CZ": "Repubblica Ceca",
    "RO": "Romania",
    "AE": "Emirati Arabi Uniti",
    "TH": "Thailandia",
    "VN": "Vietnam",
    "MY": "Malesia",
    "SG": "Singapore",
    "PH": "Filippine",
    "PK": "Pakistan",
    "DEFAULT": "Paese sconosciuto"
  },
  "listCountries": {
    "United States": "Stati Uniti",
    "France": "Francia",
    "Germany": "Germania",
    "Spain": "Spagna",
    "Italy": "Italia",
    "United Kingdom": "Regno Unito",
    "Croatia": "Croazia",
    "Canada": "Canada",
    "Australia": "Australia",
    "China": "Cina",
    "Japan": "Giappone",
    "India": "India",
    "Brazil": "Brasile",
    "Russia": "Russia",
    "Mexico": "Messico",
    "South Africa": "Sud Africa",
    "Saudi Arabia": "Arabia Saudita",
    "Egypt": "Egitto",
    "Nigeria": "Nigeria",
    "Kenya": "Kenya",
    "Morocco": "Marocco",
    "Tunisia": "Tunisia",
    "North Macedonia": "Macedonia del Nord",
    "Argentina": "Argentina",
    "Turkey": "Turchia",
    "Indonesia": "Indonesia",
    "South Korea": "Corea del Sud",
    "Netherlands": "Paesi Bassi",
    "Sweden": "Svezia",
    "Switzerland": "Svizzera",
    "Belgium": "Belgio",
    "Austria": "Austria",
    "Poland": "Polonia",
    "Norway": "Norvegia",
    "Finland": "Finlandia",
    "Denmark": "Danimarca",
    "Greece": "Grecia",
    "Portugal": "Portogallo",
    "Hungary": "Ungheria",
    "Czech Republic": "Repubblica Ceca",
    "Romania": "Romania",
    "United Arab Emirates": "Emirati Arabi Uniti",
    "Thailand": "Thailandia",
    "Vietnam": "Vietnam",
    "Malaysia": "Malesia",
    "Singapore": "Singapore",
    "Philippines": "Filippine",
    "Pakistan": "Pakistan"
  },
  "regions": {
    "MA": {
      "Agadir": "Agadir",
      "Marrakech": "Marrakech",
      "Salé": "Salé"
    },
    "KE": {
      "Nairobi": "Nairobi",
      "Mombasa": "Mombasa",
      "Kisumu": "Kisumu"
    },
    "NG": {
      "Lagos": "Lagos",
      "Abuja": "Abuja",
      "Kano": "Kano"
    },
    "ZA": {
      "Zululand District Municipality": "Municipalità distrettuale di Zululand",
      "Cape_town": "Città del Capo",
      "Johannesburg": "Johannesburg",
      "Durban": "Durban"
    },
    "TN": {
      "Tunis": "Tunisi",
      "Sfax": "Sfax",
      "Djerba": "Djerba"
    },
    "IN": {
      "Agra": "Agra",
      "Bengaluru": "Bengaluru",
      "Cuddalore": "Cuddalore",
      "Darbhanga": "Darbhanga",
      "Firozpur": "Firozpur",
      "Ghaziabad": "Ghaziabad",
      "New Delhi": "Nuova Delhi",
      "Pune": "Pune",
      "Saharanpur": "Saharanpur",
      "Bihar": "Bihar",
      "Goa": "Goa",
      "Punjab": "Punjab",
      "Uttar Pradesh": "Uttar Pradesh",
      "Delhi": "Delhi"
    },
    "SG": {
      "Bugis": "Bugis",
      "Singapore": "Singapore"
    },
    "TR": {
      "Beşiktaş": "Beşiktaş",
      "Şişli": "Şişli",
      "Besiktas": "Beşiktaş",
      "Sisli": "Beşiktaş",
      "Ümraniye": "Ümraniye",
      "Ankara": "Ankara",
      "Antalya": "Antalya",
      "Aydın": "Aydın",
      "Bursa": "Bursa",
      "İstanbul": "Istanbul",
      "İzmir": "Izmir",
      "Kayseri": "Kayseri",
      "Nevşehir": "Nevşehir",
      "Samsun": "Samsun",
      "Adana": "Adana",
      "Konya": "Konya",
      "Gaziantep": "Gaziantep",
      "Mersin": "Mersin",
      "Muratpaşa": "Muratpaşa"
    },
    "AE": {
      "Dubai": "Dubai",
      "Abu Dhabi": "Abu Dhabi",
      "Sharjah": "Sharjah",
      "Ajman": "Ajman",
      "Ras Al Khaimah": "Ras Al Khaimah",
      "Fujairah": "Fujairah",
      "Umm Al-Quwain": "Umm Al-Quwain",
      "Al Ain": "Al Ain"
    },
    "HR": {
      "Gospić": "Gospić",
      "Pula": "Pola"
    },
    "GR": {
      "Athens": "Atene",
      "Kipseli": "Kipséli",
      "Kipséli": "Kipséli"
    },
    "MK": {
      "Skopje": "Skopje"
    },
    "PT": {
      "Castelo de Paiva": "Castelo de Paiva",
      "Monção": "Monção",
      "Santa Maria da Feira": "Santa Maria da Feira"
    },
    "JO": {
      "Amman": "Amman"
    },
    "NL": {
      "Rockanje": "Rockanje",
      "South Holland": "Olanda Meridionale"
    }
  }
}
